tmu.v
// =============================================================================
// TMU — Ternary MatMul Unit (K-Parallel Dot Product, Wide BRAM)
// =============================================================================
// Computes y[j] = sum_i W[i][j] * x[i]  where W[i][j] in {-1, 0, +1}
//
// Architecture: K weights processed per cycle via SINGLE wide BRAM + adder tree
//   - x_buffer filled during S_FILL phase (N_IN cycles)
//   - S_PREFETCH loads K values from x_buffer BRAM into x_reg[] one-at-a-time
//   - S_COMPUTE: K x_reg values + K weight codes from wide BRAM → adder tree
//   - Accumulator sums tree output across ceil(N_IN/K) steps
//
// DRAM-free design: x_buffer marked ram_style=block (single read port).
//   K parallel reads replaced by K-cycle prefetch into x_reg[0:K-1] registers.
//   x_reg is K flip-flops — never inferred as distributed RAM.
//
// Wide BRAM (weight): packs K banks into one (2*K)-bit-wide memory.
//   K=32: 64-bit wide → 1 BRAM36 read port per TMU instance
//   K=16: 32-bit wide → 1 BRAM18 read port per TMU instance
//
// Cycle budget (K=16, N_IN=243, N_OUT=729, STEPS_PER_OUT=16):
//   S_FILL:     243 cycles
//   Per output: K_prefetch (K+1=17) + STEPS_PER_OUT compute = 33 cycles/step × 16 steps = 528
//   Total:      729 × 528 ≈ 385K cycles/token  (vs 81K zero-bubble; 4.75× slower, synthesises)
//
// Weight encoding: 2'b01=+1, 2'b10=-1, 2'b00=0
// Wide word layout: {w[K-1], ..., w[1], w[0]} where each w[b] is 2 bits
// Address: j * STEPS_PER_OUT + (i / K)
//
// phi^2 + 1/phi^2 = 3 = TRINITY
// =============================================================================

`timescale 1ns / 1ps

module tmu #(
    parameter N_IN            = 243,
    parameter N_OUT           = 729,
    parameter K               = 32,
    parameter ACC_WIDTH       = 20,
    parameter ADDR_WIDTH      = 18,
    parameter I_WIDTH         = 8,
    parameter J_WIDTH         = 10,
    parameter MEM_FILE_PREFIX = "tmu_w",
    parameter USE_EXT_X       = 0
)(
    input  wire                        clk,
    input  wire                        rst,
    input  wire                        start,
    output reg  signed [ACC_WIDTH-1:0] result_data,
    output reg  [J_WIDTH-1:0]          result_addr,
    output reg                         result_valid,
    output reg                         done,
    output reg                         busy,
    input  wire signed [ACC_WIDTH-1:0] x_ext_data,
    output wire [I_WIDTH-1:0]          x_ext_addr
);

    // K guard — only K=16 and K=32 supported
    initial begin
        if (K != 16 && K != 32) begin
            $display("ERROR: TMU requires K=16 or K=32, got K=%0d", K);
            $finish;
        end
    end

    // =========================================================================
    // DERIVED PARAMETERS
    // =========================================================================
    localparam STEPS_PER_OUT = (N_IN + K - 1) / K;  // ceil(N_IN / K)
    localparam BANK_DEPTH    = STEPS_PER_OUT * N_OUT;

    function integer clog2(input integer val);
        integer i;
        begin
            clog2 = 0;
            for (i = val - 1; i > 0; i = i >> 1)
                clog2 = clog2 + 1;
        end
    endfunction

    localparam BANK_ADDR_BITS = clog2(BANK_DEPTH > 0 ? BANK_DEPTH : 1);
    localparam BANK_MEM_DEPTH = 1 << BANK_ADDR_BITS;
    localparam WIDE_BITS      = 2 * K;  // 64 for K=32, 32 for K=16

    // Width for prefetch counter (0..K-1 + 1 for BRAM latency)
    localparam K_WIDTH        = (K == 32) ? 6 : 5;  // enough bits for 0..K

    // Width-safe comparison constants
    localparam [I_WIDTH-1:0] LAST_I = N_IN - 1;
    localparam [J_WIDTH-1:0] LAST_J = N_OUT - 1;

    // =========================================================================
    // X BUFFER — BRAM (single read port, registered output)
    // =========================================================================
    // Marked ram_style=block so Yosys infers Block RAM, not distributed RAM.
    // Only one read address issued per cycle → no multi-port DRAM inference.

    (* ram_style = "block" *)
    reg signed [ACC_WIDTH-1:0] x_buffer [0:N_IN-1];

    reg [I_WIDTH-1:0] fill_idx;
    assign x_ext_addr = fill_idx;

    wire signed [ACC_WIDTH-1:0] x_fill_val;
    generate
        if (USE_EXT_X) begin : gen_ext_x
            assign x_fill_val = x_ext_data;
        end else begin : gen_self_x
            assign x_fill_val = {{(ACC_WIDTH - I_WIDTH - 1){1'b0}}, fill_idx} + {{(ACC_WIDTH-1){1'b0}}, 1'b1};
        end
    endgenerate

    // Single-port BRAM read — address driven by FSM, 1-cycle read latency
    reg [I_WIDTH-1:0]          xbuf_rd_addr;
    reg signed [ACC_WIDTH-1:0] xbuf_rd_data;  // registered output (latency=1)

    always @(posedge clk) begin
        xbuf_rd_data <= x_buffer[xbuf_rd_addr];
    end

    // =========================================================================
    // X REGISTER FILE — K flip-flops loaded during S_PREFETCH
    // =========================================================================
    // K=16 or K=32 plain registers — synthesiser will NOT infer RAM for these
    // because they are only written sequentially (one per cycle) and read all
    // at once combinationally in S_COMPUTE.
    // Yosys DRAM inference requires write-enable on individual elements
    // selected by a runtime index; here each element has a fixed address
    // decoded from pf_cnt via the generate loop.

    reg signed [ACC_WIDTH-1:0] x_reg [0:K-1];

    // =========================================================================
    // WIDE BRAM — single (2*K)-bit-wide memory replaces K separate 2-bit banks
    // =========================================================================
    // One read per cycle → K weight codes extracted combinationally.
    // (* ram_style = "block" *) forces Block RAM inference in Yosys/Vivado.

    (* ram_style = "block" *)
    reg [WIDE_BITS-1:0] bank_mem_wide [0:BANK_MEM_DEPTH-1];

    initial $readmemb({MEM_FILE_PREFIX, "_wide.mem"}, bank_mem_wide);

    reg [BANK_ADDR_BITS-1:0] bank_rd_addr;
    reg [WIDE_BITS-1:0]      bank_word;

    // Registered BRAM read (1-cycle latency)
    always @(posedge clk) begin
        bank_word <= bank_mem_wide[bank_rd_addr];
    end

    // Combinational extraction: split wide word into K 2-bit codes
    wire [1:0] w_code [0:K-1];
    genvar b;
    generate
        for (b = 0; b < K; b = b + 1) begin : gen_wcode
            assign w_code[b] = bank_word[2*b +: 2];
        end
    endgenerate

    // =========================================================================
    // TERNARY MUX — K partial products using x_reg (DRAM-free)
    // =========================================================================
    // x_reg[b] is a simple register index — no runtime-indexed array read.
    // The (x_idx < N_IN) guard handles the tail partial step where
    // step_base + b >= N_IN; those x_reg entries are zero-initialised and
    // loaded with 0 during S_PREFETCH for out-of-range indices.

    wire signed [ACC_WIDTH-1:0] partial [0:K-1];

    generate
        for (b = 0; b < K; b = b + 1) begin : gen_partial
            assign partial[b] = (w_code[b] == 2'b01) ?  x_reg[b] :
                                (w_code[b] == 2'b10) ? -x_reg[b] :
                                                        {ACC_WIDTH{1'b0}};
        end
    endgenerate

    // =========================================================================
    // ADDER TREE — K=16: 4 stages, K=32: 5 stages (combinational)
    // =========================================================================
    wire signed [ACC_WIDTH-1:0] tree_sum;

    generate if (K == 16) begin : gen_tree_k16
        wire signed [ACC_WIDTH-1:0] s1 [0:7];
        wire signed [ACC_WIDTH-1:0] s2 [0:3];
        wire signed [ACC_WIDTH-1:0] s3 [0:1];

        for (b = 0; b < 8; b = b + 1) begin : gs1
            assign s1[b] = partial[2*b] + partial[2*b+1];
        end
        for (b = 0; b < 4; b = b + 1) begin : gs2
            assign s2[b] = s1[2*b] + s1[2*b+1];
        end
        for (b = 0; b < 2; b = b + 1) begin : gs3
            assign s3[b] = s2[2*b] + s2[2*b+1];
        end
        assign tree_sum = s3[0] + s3[1];

    end else begin : gen_tree_k32
        wire signed [ACC_WIDTH-1:0] s1 [0:15];
        wire signed [ACC_WIDTH-1:0] s2 [0:7];
        wire signed [ACC_WIDTH-1:0] s3 [0:3];
        wire signed [ACC_WIDTH-1:0] s4 [0:1];

        for (b = 0; b < 16; b = b + 1) begin : gs1
            assign s1[b] = partial[2*b] + partial[2*b+1];
        end
        for (b = 0; b < 8; b = b + 1) begin : gs2
            assign s2[b] = s1[2*b] + s1[2*b+1];
        end
        for (b = 0; b < 4; b = b + 1) begin : gs3
            assign s3[b] = s2[2*b] + s2[2*b+1];
        end
        for (b = 0; b < 2; b = b + 1) begin : gs4
            assign s4[b] = s3[2*b] + s3[2*b+1];
        end
        assign tree_sum = s4[0] + s4[1];

    end endgenerate

    // =========================================================================
    // STATE MACHINE
    // =========================================================================
    // S_IDLE    → S_FILL     (on start)
    // S_FILL    → S_PREFETCH (after N_IN cycles)
    // S_PREFETCH→ S_COMPUTE  (after K+1 cycles: K addr issues + 1 BRAM latency)
    // S_COMPUTE → S_PREFETCH (if more steps remain for this j)
    //           → S_OUTPUT   (last step for this j)
    // S_OUTPUT  → S_PREFETCH (next j, if j < LAST_J)
    //           → S_DONE     (if j == LAST_J)
    // S_DONE    → S_IDLE
    //
    // S_PREFETCH details:
    //   pf_cnt=0:     issue xbuf_rd_addr = step_base + 0
    //   pf_cnt=1:     x_reg[0] <= xbuf_rd_data; issue addr for x_reg[1]
    //   ...
    //   pf_cnt=K-1:   x_reg[K-2] loaded; issue addr for x_reg[K-1]
    //   pf_cnt=K:     x_reg[K-1] loaded; issue bank_rd_addr; → S_COMPUTE
    //                 (bank_word valid on first cycle of S_COMPUTE)
    //
    // S_COMPUTE details (1 cycle):
    //   acc += tree_sum  (bank_word and x_reg[] both valid)
    //   If last step → S_OUTPUT, else advance step and → S_PREFETCH

    localparam S_IDLE      = 3'd0;
    localparam S_FILL      = 3'd1;
    localparam S_PREFETCH  = 3'd2;
    localparam S_COMPUTE   = 3'd3;
    localparam S_OUTPUT    = 3'd4;
    localparam S_DONE      = 3'd5;

    reg [2:0] state;
    reg signed [ACC_WIDTH-1:0] acc;
    reg [J_WIDTH-1:0]          j_idx;
    reg [BANK_ADDR_BITS-1:0]   step_cnt;       // which K-group within current j
    reg [BANK_ADDR_BITS-1:0]   j_base_addr;    // j * STEPS_PER_OUT
    reg [I_WIDTH-1:0]          step_base;      // step_cnt * K (x index of first element)
    reg [K_WIDTH-1:0]          pf_cnt;         // prefetch counter 0..K

    localparam [BANK_ADDR_BITS-1:0] STEPS_M1 = STEPS_PER_OUT - 1;

    // Prefetch address computation — module-scope wire, no inline reg declarations.
    // Computes step_base + pf_cnt with one extra bit to detect out-of-range.
    wire [I_WIDTH:0] pf_xidx_wide;
    assign pf_xidx_wide = {1'b0, step_base} + {{(I_WIDTH-K_WIDTH+1){1'b0}}, pf_cnt};

    // Generate loop for x_reg write — each register pb gets written when
    // pf_cnt == pb+1 (one cycle after addr pb was issued, BRAM latency=1).
    // Using individual equality comparisons avoids a runtime-indexed LHS,
    // which is what triggers distributed-RAM inference in Yosys.
    genvar pb;
    generate
        for (pb = 0; pb < K; pb = pb + 1) begin : gen_xreg_load
            always @(posedge clk) begin
                if (rst) begin
                    x_reg[pb] <= {ACC_WIDTH{1'b0}};
                end else if (state == S_PREFETCH && pf_cnt == (pb[K_WIDTH-1:0] + {{(K_WIDTH-1){1'b0}},1'b1})) begin
                    // xbuf_rd_data is the result of the address issued when pf_cnt==pb
                    x_reg[pb] <= xbuf_rd_data;
                end
            end
        end
    endgenerate

    always @(posedge clk) begin
        if (rst) begin
            state         <= S_IDLE;
            fill_idx      <= {I_WIDTH{1'b0}};
            j_idx         <= {J_WIDTH{1'b0}};
            step_cnt      <= {BANK_ADDR_BITS{1'b0}};
            j_base_addr   <= {BANK_ADDR_BITS{1'b0}};
            step_base     <= {I_WIDTH{1'b0}};
            pf_cnt        <= {K_WIDTH{1'b0}};
            xbuf_rd_addr  <= {I_WIDTH{1'b0}};
            bank_rd_addr  <= {BANK_ADDR_BITS{1'b0}};
            acc           <= {ACC_WIDTH{1'b0}};
            done          <= 1'b0;
            busy          <= 1'b0;
            result_valid  <= 1'b0;
            result_data   <= {ACC_WIDTH{1'b0}};
            result_addr   <= {J_WIDTH{1'b0}};
        end else begin
            done         <= 1'b0;
            result_valid <= 1'b0;

            case (state)
                // ---------------------------------------------------------
                S_IDLE: begin
                    if (start) begin
                        fill_idx <= {I_WIDTH{1'b0}};
                        busy     <= 1'b1;
                        state    <= S_FILL;
                    end
                end

                // ---------------------------------------------------------
                // S_FILL: write N_IN values into x_buffer BRAM one per cycle
                S_FILL: begin
                    x_buffer[fill_idx] <= x_fill_val;
                    if (fill_idx == LAST_I) begin
                        j_idx        <= {J_WIDTH{1'b0}};
                        j_base_addr  <= {BANK_ADDR_BITS{1'b0}};
                        step_cnt     <= {BANK_ADDR_BITS{1'b0}};
                        step_base    <= {I_WIDTH{1'b0}};
                        acc          <= {ACC_WIDTH{1'b0}};
                        pf_cnt       <= {K_WIDTH{1'b0}};
                        xbuf_rd_addr <= {I_WIDTH{1'b0}};
                        state        <= S_PREFETCH;
                    end else begin
                        fill_idx <= fill_idx + {{(I_WIDTH-1){1'b0}}, 1'b1};
                    end
                end

                // ---------------------------------------------------------
                // S_PREFETCH: load K values from x_buffer BRAM into x_reg[]
                //
                // On cycles pf_cnt = 0..K-1:
                //   Issue xbuf_rd_addr = step_base + pf_cnt (clamped to 0 if OOB)
                //   gen_xreg_load flops capture xbuf_rd_data one cycle later
                //
                // On cycle pf_cnt = K:
                //   All K x_reg entries are valid
                //   Issue bank_rd_addr = j_base_addr + step_cnt
                //   Transition to S_COMPUTE (bank_word valid next cycle)
                S_PREFETCH: begin
                    if (pf_cnt < K[K_WIDTH-1:0]) begin
                        // Issue x_buffer read address (clamped if out-of-range)
                        xbuf_rd_addr <= (pf_xidx_wide < N_IN[I_WIDTH:0])
                                        ? pf_xidx_wide[I_WIDTH-1:0]
                                        : {I_WIDTH{1'b0}};
                        pf_cnt <= pf_cnt + {{(K_WIDTH-1){1'b0}}, 1'b1};
                    end else begin
                        // All K x_reg values loaded; arm weight BRAM read
                        bank_rd_addr <= j_base_addr + step_cnt;
                        pf_cnt       <= {K_WIDTH{1'b0}};
                        state        <= S_COMPUTE;
                    end
                end

                // ---------------------------------------------------------
                // S_COMPUTE: one cycle
                //   bank_word valid (issued on last pf_cnt==K cycle, latency=1)
                //   x_reg[] valid (loaded during S_PREFETCH)
                //   acc accumulates tree_sum
                S_COMPUTE: begin
                    acc <= acc + tree_sum;

                    if (step_cnt == STEPS_M1) begin
                        state <= S_OUTPUT;
                    end else begin
                        step_cnt     <= step_cnt + {{(BANK_ADDR_BITS-1){1'b0}}, 1'b1};
                        step_base    <= step_base + K[I_WIDTH-1:0];
                        pf_cnt       <= {K_WIDTH{1'b0}};
                        // Prime the first xbuf read of the next prefetch
                        xbuf_rd_addr <= step_base + K[I_WIDTH-1:0];
                        state        <= S_PREFETCH;
                    end
                end

                // ---------------------------------------------------------
                // S_OUTPUT: emit accumulated result for j_idx
                // acc holds the final dot product (updated in last S_COMPUTE)
                S_OUTPUT: begin
                    result_data  <= acc;
                    result_addr  <= j_idx;
                    result_valid <= 1'b1;

                    if (j_idx == LAST_J) begin
                        state <= S_DONE;
                    end else begin
                        j_idx        <= j_idx + {{(J_WIDTH-1){1'b0}}, 1'b1};
                        j_base_addr  <= j_base_addr + STEPS_PER_OUT[BANK_ADDR_BITS-1:0];
                        step_cnt     <= {BANK_ADDR_BITS{1'b0}};
                        step_base    <= {I_WIDTH{1'b0}};
                        acc          <= {ACC_WIDTH{1'b0}};
                        pf_cnt       <= {K_WIDTH{1'b0}};
                        xbuf_rd_addr <= {I_WIDTH{1'b0}};
                        state        <= S_PREFETCH;
                    end
                end

                // ---------------------------------------------------------
                S_DONE: begin
                    done  <= 1'b1;
                    busy  <= 1'b0;
                    state <= S_IDLE;
                end

            endcase
        end
    end

endmodule

tmu_tb.v
// =============================================================================
// TMU Testbench — K=16 Parallel Ternary MatMul Unit verification
// =============================================================================
// Small parameters: N_IN=16, N_OUT=4, K=16
// With K=16 and N_IN=16: steps_per_out=1, each bank handles exactly 1 input.
// Bank b = weights for input i=b.
//
// Tests: known reference, back-to-back start
// =============================================================================

`timescale 1ns / 1ps

module tmu_tb;

    parameter N_IN       = 16;
    parameter N_OUT      = 4;
    parameter K          = 16;
    parameter ACC_WIDTH  = 20;
    parameter I_WIDTH    = 5;
    parameter J_WIDTH    = 3;
    parameter ADDR_WIDTH = 8;

    reg                        clk, rst, start;
    wire signed [ACC_WIDTH-1:0] result_data;
    wire [J_WIDTH-1:0]          result_addr;
    wire                        result_valid;
    wire                        done, busy;

    // Self-test mode (USE_EXT_X=0): x[i] = i + 1
    wire signed [ACC_WIDTH-1:0] x_ext_data;
    wire [I_WIDTH-1:0]          x_ext_addr;
    assign x_ext_data = {ACC_WIDTH{1'b0}};

    tmu #(
        .N_IN           (N_IN),
        .N_OUT          (N_OUT),
        .K              (K),
        .ACC_WIDTH      (ACC_WIDTH),
        .ADDR_WIDTH     (ADDR_WIDTH),
        .I_WIDTH        (I_WIDTH),
        .J_WIDTH        (J_WIDTH),
        .MEM_FILE_PREFIX("tmu_test_w"),
        .USE_EXT_X      (0)
    ) uut (
        .clk         (clk),
        .rst         (rst),
        .start       (start),
        .result_data (result_data),
        .result_addr (result_addr),
        .result_valid(result_valid),
        .done        (done),
        .busy        (busy),
        .x_ext_data  (x_ext_data),
        .x_ext_addr  (x_ext_addr)
    );

    // Clock: 10 ns period
    initial clk = 0;
    always #5 clk = ~clk;

    // Capture results
    reg signed [ACC_WIDTH-1:0] results [0:N_OUT-1];

    always @(posedge clk) begin
        if (result_valid) begin
            results[result_addr] <= result_data;
        end
    end

    // =========================================================================
    // Test execution
    // =========================================================================
    integer pass_count;
    integer fail_count;

    task reset_dut;
        begin
            rst = 1;
            start = 0;
            #20;
            rst = 0;
            #10;
        end
    endtask

    task run_matvec;
        begin
            @(posedge clk);
            start = 1;
            @(posedge clk);
            start = 0;
            while (!done) @(posedge clk);
            @(posedge clk);
        end
    endtask

    task check_result;
        input [J_WIDTH-1:0] idx;
        input signed [ACC_WIDTH-1:0] expected;
        input [8*32-1:0] test_name;
        begin
            if (results[idx] === expected) begin
                $display("  PASS: %0s — y[%0d] = %0d (expected %0d)", test_name, idx, results[idx], expected);
                pass_count = pass_count + 1;
            end else begin
                $display("  FAIL: %0s — y[%0d] = %0d (expected %0d)", test_name, idx, results[idx], expected);
                fail_count = fail_count + 1;
            end
        end
    endtask

    initial begin
        $dumpfile("tmu_tb.vcd");
        $dumpvars(0, tmu_tb);

        pass_count = 0;
        fail_count = 0;

        // =================================================================
        // Test 1: Known weights → hand-computed reference
        // =================================================================
        // K=16, N_IN=16: steps_per_out = ceil(16/16) = 1
        // Bank b handles input i=b. Each bank has N_OUT=4 entries (one per output j).
        //
        // Weight matrix:
        //   j=0: all +1        → y[0] = sum(1..16) = 136
        //   j=1: alt +1/-1     → y[1] = 1-2+3-4+...+15-16 = -8
        //   j=2: first 8 = +1  → y[2] = sum(1..8) = 36
        //   j=3: all -1        → y[3] = -sum(1..16) = -136

        $display("\n=== TEST 1: Known weights (hand-computed) ===");
        reset_dut;
        run_matvec;

        check_result(0,  136, "all +1");
        check_result(1,   -8, "alternating +1/-1");
        check_result(2,   36, "first 8 = +1, rest 0");
        check_result(3, -136, "all -1");

        // =================================================================
        // Test 2: Back-to-back start — no state corruption
        // =================================================================
        $display("\n=== TEST 2: Back-to-back start ===");
        run_matvec;

        check_result(0,  136, "b2b all +1");
        check_result(1,   -8, "b2b alternating");
        check_result(2,   36, "b2b first 8");
        check_result(3, -136, "b2b all -1");

        // =================================================================
        // Summary
        // =================================================================
        $display("\n============================================");
        if (fail_count == 0)
            $display("ALL TESTS PASSED (%0d/%0d)", pass_count, pass_count);
        else
            $display("FAILED: %0d/%0d tests failed", fail_count, pass_count + fail_count);
        $display("============================================\n");

        $finish;
    end

    // Timeout watchdog
    initial begin
        #200000;
        $display("TIMEOUT: simulation exceeded 200us");
        $finish;
    end

endmodule

apps/website/public/widgets/vcd-wrapped/samples/tmu.vcd
$date
	Mon Oct  5 01:46:09 2026
$end
$version
	Icarus Verilog
$end
$timescale
	1ps
$end
$scope module tmu_tb $end
$var wire 20 ! x_ext_data [19:0] $end
$var wire 5 " x_ext_addr [4:0] $end
$var wire 1 # result_valid $end
$var wire 20 $ result_data [19:0] $end
$var wire 3 % result_addr [2:0] $end
$var wire 1 & done $end
$var wire 1 ' busy $end
$var parameter 32 ( ACC_WIDTH $end
$var parameter 32 ) ADDR_WIDTH $end
$var parameter 32 * I_WIDTH $end
$var parameter 32 + J_WIDTH $end
$var parameter 32 , K $end
$var parameter 32 - N_IN $end
$var parameter 32 . N_OUT $end
$var reg 1 / clk $end
$var reg 1 0 rst $end
$var reg 1 1 start $end
$var integer 32 2 fail_count [31:0] $end
$var integer 32 3 pass_count [31:0] $end
$scope module uut $end
$var wire 1 / clk $end
$var wire 1 0 rst $end
$var wire 1 1 start $end
$var wire 5 4 x_ext_addr [4:0] $end
$var wire 20 5 x_ext_data [19:0] $end
$var wire 20 6 x_fill_val [19:0] $end
$var wire 20 7 tree_sum [19:0] $end
$var wire 6 8 pf_xidx_wide [5:0] $end
$var parameter 32 9 ACC_WIDTH $end
$var parameter 32 : ADDR_WIDTH $end
$var parameter 32 ; BANK_ADDR_BITS $end
$var parameter 66 < BANK_DEPTH $end
$var parameter 34 = BANK_MEM_DEPTH $end
$var parameter 32 > I_WIDTH $end
$var parameter 32 ? J_WIDTH $end
$var parameter 32 @ K $end
$var parameter 32 A K_WIDTH $end
$var parameter 5 B LAST_I $end
$var parameter 3 C LAST_J $end
$var parameter 80 D MEM_FILE_PREFIX $end
$var parameter 32 E N_IN $end
$var parameter 32 F N_OUT $end
$var parameter 2 G STEPS_M1 $end
$var parameter 34 H STEPS_PER_OUT $end
$var parameter 3 I S_COMPUTE $end
$var parameter 3 J S_DONE $end
$var parameter 3 K S_FILL $end
$var parameter 3 L S_IDLE $end
$var parameter 3 M S_OUTPUT $end
$var parameter 3 N S_PREFETCH $end
$var parameter 32 O USE_EXT_X $end
$var parameter 64 P WIDE_BITS $end
$var reg 20 Q acc [19:0] $end
$var reg 2 R bank_rd_addr [1:0] $end
$var reg 32 S bank_word [31:0] $end
$var reg 1 ' busy $end
$var reg 1 & done $end
$var reg 5 T fill_idx [4:0] $end
$var reg 2 U j_base_addr [1:0] $end
$var reg 3 V j_idx [2:0] $end
$var reg 5 W pf_cnt [4:0] $end
$var reg 3 X result_addr [2:0] $end
$var reg 20 Y result_data [19:0] $end
$var reg 1 # result_valid $end
$var reg 3 Z state [2:0] $end
$var reg 5 [ step_base [4:0] $end
$var reg 2 \ step_cnt [1:0] $end
$var reg 5 ] xbuf_rd_addr [4:0] $end
$var reg 20 ^ xbuf_rd_data [19:0] $end
$scope function clog2 $end
$var integer 32 _ i [31:0] $end
$var integer 32 ` val [31:0] $end
$upscope $end
$scope begin gen_partial[0] $end
$var parameter 2 a b $end
$upscope $end
$scope begin gen_partial[1] $end
$var parameter 2 b b $end
$upscope $end
$scope begin gen_partial[2] $end
$var parameter 3 c b $end
$upscope $end
$scope begin gen_partial[3] $end
$var parameter 3 d b $end
$upscope $end
$scope begin gen_partial[4] $end
$var parameter 4 e b $end
$upscope $end
$scope begin gen_partial[5] $end
$var parameter 4 f b $end
$upscope $end
$scope begin gen_partial[6] $end
$var parameter 4 g b $end
$upscope $end
$scope begin gen_partial[7] $end
$var parameter 4 h b $end
$upscope $end
$scope begin gen_partial[8] $end
$var parameter 5 i b $end
$upscope $end
$scope begin gen_partial[9] $end
$var parameter 5 j b $end
$upscope $end
$scope begin gen_partial[10] $end
$var parameter 5 k b $end
$upscope $end
$scope begin gen_partial[11] $end
$var parameter 5 l b $end
$upscope $end
$scope begin gen_partial[12] $end
$var parameter 5 m b $end
$upscope $end
$scope begin gen_partial[13] $end
$var parameter 5 n b $end
$upscope $end
$scope begin gen_partial[14] $end
$var parameter 5 o b $end
$upscope $end
$scope begin gen_partial[15] $end
$var parameter 5 p b $end
$upscope $end
$scope begin gen_self_x $end
$upscope $end
$scope begin gen_tree_k16 $end
$scope begin gs1[0] $end
$var parameter 2 q b $end
$upscope $end
$scope begin gs1[1] $end
$var parameter 2 r b $end
$upscope $end
$scope begin gs1[2] $end
$var parameter 3 s b $end
$upscope $end
$scope begin gs1[3] $end
$var parameter 3 t b $end
$upscope $end
$scope begin gs1[4] $end
$var parameter 4 u b $end
$upscope $end
$scope begin gs1[5] $end
$var parameter 4 v b $end
$upscope $end
$scope begin gs1[6] $end
$var parameter 4 w b $end
$upscope $end
$scope begin gs1[7] $end
$var parameter 4 x b $end
$upscope $end
$scope begin gs2[0] $end
$var parameter 2 y b $end
$upscope $end
$scope begin gs2[1] $end
$var parameter 2 z b $end
$upscope $end
$scope begin gs2[2] $end
$var parameter 3 { b $end
$upscope $end
$scope begin gs2[3] $end
$var parameter 3 | b $end
$upscope $end
$scope begin gs3[0] $end
$var parameter 2 } b $end
$upscope $end
$scope begin gs3[1] $end
$var parameter 2 ~ b $end
$upscope $end
$upscope $end
$scope begin gen_wcode[0] $end
$var parameter 2 !" b $end
$upscope $end
$scope begin gen_wcode[1] $end
$var parameter 2 "" b $end
$upscope $end
$scope begin gen_wcode[2] $end
$var parameter 3 #" b $end
$upscope $end
$scope begin gen_wcode[3] $end
$var parameter 3 $" b $end
$upscope $end
$scope begin gen_wcode[4] $end
$var parameter 4 %" b $end
$upscope $end
$scope begin gen_wcode[5] $end
$var parameter 4 &" b $end
$upscope $end
$scope begin gen_wcode[6] $end
$var parameter 4 '" b $end
$upscope $end
$scope begin gen_wcode[7] $end
$var parameter 4 (" b $end
$upscope $end
$scope begin gen_wcode[8] $end
$var parameter 5 )" b $end
$upscope $end
$scope begin gen_wcode[9] $end
$var parameter 5 *" b $end
$upscope $end
$scope begin gen_wcode[10] $end
$var parameter 5 +" b $end
$upscope $end
$scope begin gen_wcode[11] $end
$var parameter 5 ," b $end
$upscope $end
$scope begin gen_wcode[12] $end
$var parameter 5 -" b $end
$upscope $end
$scope begin gen_wcode[13] $end
$var parameter 5 ." b $end
$upscope $end
$scope begin gen_wcode[14] $end
$var parameter 5 /" b $end
$upscope $end
$scope begin gen_wcode[15] $end
$var parameter 5 0" b $end
$upscope $end
$scope begin gen_xreg_load[0] $end
$var parameter 2 1" pb $end
$upscope $end
$scope begin gen_xreg_load[1] $end
$var parameter 2 2" pb $end
$upscope $end
$scope begin gen_xreg_load[2] $end
$var parameter 3 3" pb $end
$upscope $end
$scope begin gen_xreg_load[3] $end
$var parameter 3 4" pb $end
$upscope $end
$scope begin gen_xreg_load[4] $end
$var parameter 4 5" pb $end
$upscope $end
$scope begin gen_xreg_load[5] $end
$var parameter 4 6" pb $end
$upscope $end
$scope begin gen_xreg_load[6] $end
$var parameter 4 7" pb $end
$upscope $end
$scope begin gen_xreg_load[7] $end
$var parameter 4 8" pb $end
$upscope $end
$scope begin gen_xreg_load[8] $end
$var parameter 5 9" pb $end
$upscope $end
$scope begin gen_xreg_load[9] $end
$var parameter 5 :" pb $end
$upscope $end
$scope begin gen_xreg_load[10] $end
$var parameter 5 ;" pb $end
$upscope $end
$scope begin gen_xreg_load[11] $end
$var parameter 5 <" pb $end
$upscope $end
$scope begin gen_xreg_load[12] $end
$var parameter 5 =" pb $end
$upscope $end
$scope begin gen_xreg_load[13] $end
$var parameter 5 >" pb $end
$upscope $end
$scope begin gen_xreg_load[14] $end
$var parameter 5 ?" pb $end
$upscope $end
$scope begin gen_xreg_load[15] $end
$var parameter 5 @" pb $end
$upscope $end
$upscope $end
$scope task check_result $end
$var reg 20 A" expected [19:0] $end
$var reg 3 B" idx [2:0] $end
$var reg 256 C" test_name [255:0] $end
$upscope $end
$scope task reset_dut $end
$upscope $end
$scope task run_matvec $end
$upscope $end
$upscope $end
$enddefinitions $end
$comment Show the parameter values. $end
$dumpall
b1111 @"
b1110 ?"
b1101 >"
b1100 ="
b1011 <"
b1010 ;"
b1001 :"
b1000 9"
b111 8"
b110 7"
b101 6"
b100 5"
b11 4"
b10 3"
b1 2"
b0 1"
b1111 0"
b1110 /"
b1101 ."
b1100 -"
b1011 ,"
b1010 +"
b1001 *"
b1000 )"
b111 ("
b110 '"
b101 &"
b100 %"
b11 $"
b10 #"
b1 ""
b0 !"
b1 ~
b0 }
b11 |
b10 {
b1 z
b0 y
b111 x
b110 w
b101 v
b100 u
b11 t
b10 s
b1 r
b0 q
b1111 p
b1110 o
b1101 n
b1100 m
b1011 l
b1010 k
b1001 j
b1000 i
b111 h
b110 g
b101 f
b100 e
b11 d
b10 c
b1 b
b0 a
b100000 P
b0 O
b10 N
b100 M
b0 L
b1 K
b101 J
b11 I
b1 H
b0 G
b100 F
b10000 E
b1110100011011010111010101011111011101000110010101110011011101000101111101110111 D
b11 C
b1111 B
b101 A
b10000 @
b11 ?
b101 >
b100 =
b100 <
b10 ;
b1000 :
b10100 9
b100 .
b10000 -
b10000 ,
b11 +
b101 *
b1000 )
b10100 (
$end
#0
$dumpvars
bx C"
bx B"
bx A"
bx `
bx _
bx ^
bx ]
bx \
bx [
bx Z
bx Y
bx X
bx W
bx V
bx U
bx T
bx S
bx R
bx Q
bx 8
bx 7
bx 6
b0 5
bx 4
b0 3
b0 2
01
10
0/
x'
x&
bx %
bx $
x#
bx "
b0 !
$end
#5000
b0 7
b0 %
b0 X
b0 $
b0 Y
0#
0'
0&
b0 Q
b0 R
b0 ]
b0 8
b0 W
b0 [
b0 U
b0 \
b0 V
b1 6
b0 "
b0 4
b0 T
b0 Z
1/
#10000
0/
#15000
1/
#20000
0/
00
#25000
1/
#30000
0/
#35000
b1 Z
1'
11
1/
#40000
0/
#45000
b10 6
b1 "
b1 4
b1 T
01
1/
#50000
0/
#55000
b11 6
b10 "
b10 4
b10 T
b1 ^
1/
#60000
0/
#65000
b100 6
b11 "
b11 4
b11 T
1/
#70000
0/
#75000
b101 6
b100 "
b100 4
b100 T
1/
#80000
0/
#85000
b110 6
b101 "
b101 4
b101 T
1/
#90000
0/
#95000
b111 6
b110 "
b110 4
b110 T
1/
#100000
0/
#105000
b1000 6
b111 "
b111 4
b111 T
1/
#110000
0/
#115000
b1001 6
b1000 "
b1000 4
b1000 T
1/
#120000
0/
#125000
b1010 6
b1001 "
b1001 4
b1001 T
1/
#130000
0/
#135000
b1011 6
b1010 "
b1010 4
b1010 T
1/
#140000
0/
