fpga/fly-vivado/verilog/trinity_qmtech.v
// =========================================================================
// TRINITY FPGA — QMTECH XC7A100T Core Board LED Blink
// Minimal test: LED heartbeat (no reset button — Core Board has no SW1)
// Clock: 50 MHz (M22) | LED: J19 (active-low)
// phi^2 + 1/phi^2 = 3 = TRINITY
// =========================================================================

`timescale 1ns / 1ps
`default_nettype none

module trinity_top (
    input  wire clk,     // 50 MHz system clock (M22)
    output wire led      // User LED D5 (J19, active-low)
);

    reg [25:0] counter = 26'd0;

    // LED heartbeat: blink ~1.5 Hz (50MHz / 2^25 ~ 1.49 Hz)
    // Active-low LED: invert counter bit so LED visibly blinks
    assign led = ~counter[24];

    always @(posedge clk) begin
        counter <= counter + 1'b1;
    end

endmodule

fpga/fly-vivado/verilog/tb_trinity.v
// =========================================================================
// Testbench for trinity_top — LED blink verification
// Simulates 50 MHz clock, checks that LED toggles correctly
// Run: iverilog -o tb_trinity tb_trinity.v trinity_qmtech.v && vvp tb_trinity
// View: gtkwave tb_trinity.vcd
// =========================================================================

`timescale 1ns / 1ps

module tb_trinity;

    reg clk;
    wire led;

    // Instantiate DUT
    trinity_top dut (
        .clk(clk),
        .led(led)
    );

    // 50 MHz clock = 20ns period
    initial clk = 0;
    always #10 clk = ~clk;

    // Monitor
    integer cycle_count;
    reg led_prev;
    integer toggle_count;
    integer first_toggle_cycle;

    initial begin
        $dumpfile("tb_trinity.vcd");
        $dumpvars(0, tb_trinity);

        cycle_count = 0;
        toggle_count = 0;
        led_prev = 1'bx;
        first_toggle_cycle = 0;

        $display("═══════════════════════════════════════════════");
        $display(" TRINITY TESTBENCH — LED Blink Verification");
        $display(" Clock: 50 MHz (20ns period)");
        $display(" Expected: LED toggles every 2^24 = 16,777,216 cycles");
        $display("           = ~336ms = ~1.49 Hz blink rate");
        $display("═══════════════════════════════════════════════");
        $display("");

        // Check initial state
        #1;
        $display("[t=0] counter=%d, led=%b (active-low: LED %s)",
                 dut.counter, led, led ? "OFF" : "ON");

        // Simulate enough cycles to see LED toggle
        // 2^24 = 16,777,216 cycles at 20ns = 335.5ms
        // We'll simulate 2^25 + a bit to see at least 2 toggles
        // But that's 33M+ cycles — too slow for full sim
        // Instead: simulate 100 cycles for basic check, then
        // force counter near toggle point to verify transition

        // Phase 1: Basic clock counting (100 cycles)
        $display("");
        $display("[Phase 1] Basic counter operation (100 cycles)...");
        repeat(100) @(posedge clk);
        $display("  After 100 clocks: counter=%d (expected 100) %s",
                 dut.counter, (dut.counter == 100) ? "OK" : "FAIL");

        // Phase 2: Force counter near first toggle point
        $display("");
        $display("[Phase 2] Fast-forward to toggle point...");
        force dut.counter = 26'h0FF_FFFE;  // 2 cycles before bit[24] flips
        @(posedge clk);
        release dut.counter;
        $display("  counter=0x%07h, led=%b (bit24=%b)", dut.counter, led, dut.counter[24]);

        @(posedge clk);  // counter becomes 0x0FF_FFFF
        $display("  counter=0x%07h, led=%b (bit24=%b)", dut.counter, led, dut.counter[24]);

        @(posedge clk);  // counter becomes 0x100_0000 — bit[24] goes HIGH
        $display("  counter=0x%07h, led=%b (bit24=%b) << LED TOGGLES HERE",
                 dut.counter, led, dut.counter[24]);

        @(posedge clk);  // counter becomes 0x100_0001
        $display("  counter=0x%07h, led=%b (bit24=%b)", dut.counter, led, dut.counter[24]);

        // Verify LED is inverted counter[24]
        if (led == ~dut.counter[24])
            $display("  LED = ~counter[24]: PASS");
        else
            $display("  LED = ~counter[24]: FAIL (led=%b, expected %b)", led, ~dut.counter[24]);

        // Phase 3: Check second toggle (bit[24] goes back LOW)
        $display("");
        $display("[Phase 3] Second toggle point...");
        force dut.counter = 26'h1FF_FFFE;
        @(posedge clk);
        release dut.counter;

        @(posedge clk);  // 0x1FF_FFFF
        $display("  counter=0x%07h, led=%b (bit24=%b)", dut.counter, led, dut.counter[24]);

        @(posedge clk);  // 0x200_0000 — bit[24] goes LOW again
        $display("  counter=0x%07h, led=%b (bit24=%b) << LED TOGGLES BACK",
                 dut.counter, led, dut.counter[24]);

        // Phase 4: Counter wrap-around
        $display("");
        $display("[Phase 4] Counter wrap-around (26-bit)...");
        force dut.counter = 26'h3FF_FFFE;
        @(posedge clk);
        release dut.counter;

        @(posedge clk);  // 0x3FF_FFFF (max)
        $display("  counter=0x%07h (max 26-bit)", dut.counter);

        @(posedge clk);  // should wrap to 0
        $display("  counter=0x%07h (wrapped to 0) %s",
                 dut.counter, (dut.counter == 0) ? "OK" : "FAIL");

        // Summary
        $display("");
        $display("═══════════════════════════════════════════════");
        $display(" SIMULATION COMPLETE");
        $display(" Counter: 26-bit, increments every clock edge");
        $display(" LED: active-low, toggles at ~1.49 Hz");
        $display(" VCD file: tb_trinity.vcd (open with GTKWave)");
        $display("═══════════════════════════════════════════════");

        #100;
        $finish;
    end

endmodule

fpga/fly-vivado/verilog/tb_trinity.vcd
$date
	Sun Mar  1 18:04:06 2026
$end
$version
	Icarus Verilog
$end
$timescale
	1ps
$end
$scope module tb_trinity $end
$var wire 1 ! led $end
$var reg 1 " clk $end
$var reg 1 # led_prev $end
$var integer 32 $ cycle_count [31:0] $end
$var integer 32 % first_toggle_cycle [31:0] $end
$var integer 32 & toggle_count [31:0] $end
$scope module dut $end
$var wire 1 " clk $end
$var wire 1 ! led $end
$var reg 26 ' counter [25:0] $end
$upscope $end
$upscope $end
$enddefinitions $end
$comment Show the parameter values. $end
$dumpall
$end
#0
$dumpvars
b0 '
b0 &
b0 %
b0 $
x#
0"
1!
$end
#10000
b1 '
1"
#20000
0"
#30000
b10 '
1"
#40000
0"
#50000
b11 '
1"
#60000
0"
#70000
b100 '
1"
#80000
0"
#90000
b101 '
1"
#100000
0"
#110000
b110 '
1"
#120000
0"
#130000
b111 '
1"
#140000
0"
#150000
b1000 '
1"
#160000
0"
#170000
b1001 '
1"
#180000
0"
#190000
b1010 '
1"
#200000
0"
#210000
b1011 '
1"
#220000
0"
#230000
b1100 '
1"
#240000
0"
#250000
b1101 '
1"
#260000
0"
#270000
b1110 '
1"
#280000
0"
#290000
b1111 '
1"
#300000
0"
#310000
b10000 '
1"
#320000
0"
#330000
b10001 '
1"
#340000
0"
#350000
b10010 '
1"
#360000
0"
#370000
b10011 '
1"
#380000
0"
#390000
b10100 '
1"
#400000
0"
#410000
b10101 '
1"
#420000
0"
#430000
b10110 '
1"
#440000
0"
#450000
b10111 '
1"
#460000
0"
#470000
b11000 '
1"
#480000
0"
#490000
b11001 '
1"
#500000
0"
#510000
b11010 '
1"
#520000
0"
#530000
b11011 '
1"
#540000
0"
#550000
b11100 '
1"
#560000
0"
#570000
b11101 '
1"
#580000
0"
#590000
b11110 '
1"
#600000
0"
#610000
b11111 '
1"
#620000
0"
#630000
b100000 '
1"
#640000
0"
#650000
b100001 '
1"
#660000
0"
#670000
b100010 '
1"
#680000
0"
#690000
b100011 '
1"
#700000
0"
#710000
b100100 '
1"
#720000
0"
#730000
b100101 '
1"
#740000
0"
#750000
b100110 '
1"
#760000
0"
#770000
b100111 '
1"
#780000
0"
#790000
b101000 '
1"
#800000
0"
#810000
b101001 '
1"
#820000
0"
#830000
b101010 '
1"
#840000
0"
#850000
b101011 '
1"
#860000
0"
#870000
b101100 '
1"
#880000
0"
#890000
b101101 '
1"
#900000
0"
#910000
b101110 '
1"
#920000
0"
#930000
b101111 '
1"
#940000
0"
#950000
b110000 '
1"
#960000
0"
#970000
b110001 '
1"
#980000
0"
#990000
b110010 '
1"
#1000000
0"
#1010000
b110011 '
1"
#1020000
0"
#1030000
b110100 '
1"
#1040000
0"
#1050000
b110101 '
1"
#1060000
0"
#1070000
b110110 '
1"
#1080000
0"
#1090000
b110111 '
1"
#1100000
0"
#1110000
b111000 '
1"
#1120000
0"
#1130000
b111001 '
1"
#1140000
0"
#1150000
b111010 '
1"
#1160000
0"
#1170000
b111011 '
1"
#1180000
0"
#1190000
b111100 '
1"
#1200000
0"
#1210000
b111101 '
1"
#1220000
0"
#1230000
b111110 '
1"
#1240000
0"
#1250000
b111111 '
1"
#1260000
0"
#1270000
b1000000 '
1"
#1280000
0"
#1290000
b1000001 '
1"
#1300000
0"
#1310000
b1000010 '
1"
#1320000
0"
#1330000
b1000011 '
1"
#1340000
0"
#1350000
b1000100 '
1"
#1360000
0"
#1370000
b1000101 '
1"
#1380000
0"
#1390000
b1000110 '
1"
#1400000
0"
#1410000
b1000111 '
1"
#1420000
0"
#1430000
b1001000 '
1"
#1440000
0"
#1450000
b1001001 '
1"
#1460000
0"
#1470000
b1001010 '
1"
#1480000
0"
#1490000
b1001011 '
1"
#1500000
0"
#1510000
b1001100 '
1"
#1520000
0"
#1530000
b1001101 '
1"
#1540000
0"
#1550000
b1001110 '
1"
#1560000
0"
#1570000
b1001111 '
1"
#1580000
0"
#1590000
b1010000 '
1"
#1600000
0"
#1610000
b1010001 '
1"
#1620000
0"
#1630000
b1010010 '
1"
#1640000
0"
#1650000
b1010011 '
1"
#1660000
0"
#1670000
b1010100 '
1"
#1680000
0"
#1690000
b1010101 '
1"
#1700000
0"
#1710000
b1010110 '
1"
#1720000
0"
#1730000
b1010111 '
1"
#1740000
0"
#1750000
b1011000 '
1"
#1760000
0"
#1770000
b1011001 '
1"
#1780000
0"
#1790000
b1011010 '
1"
#1800000
0"
#1810000
b1011011 '
1"
#1820000
0"
#1830000
b1011100 '
1"
#1840000
0"
#1850000
b1011101 '
1"
#1860000
0"
#1870000
b1011110 '
1"
#1880000
0"
#1890000
b1011111 '
1"
#1900000
0"
#1910000
b1100000 '
1"
#1920000
0"
#1930000
b1100001 '
1"
#1940000
0"
#1950000
b1100010 '
1"
#1960000
0"
#1970000
b1100011 '
1"
#1980000
0"
#1990000
b111111111111111111111110 '
1"
#2000000
0"
#2010000
b111111111111111111111111 '
1"
#2020000
0"
#2030000
0!
b1000000000000000000000000 '
1"
#2040000
0"
#2050000
b1000000000000000000000001 '
1"
#2060000
0"
#2070000
b1111111111111111111111110 '
1"
#2080000
0"
#2090000
b1111111111111111111111111 '
1"
#2100000
0"
#2110000
1!
b10000000000000000000000000 '
1"
#2120000
0"
#2130000
0!
b11111111111111111111111110 '
1"
#2140000
0"
#2150000
b11111111111111111111111111 '
1"
#2160000
0"
#2170000
1!
b0 '
1"
#2180000
0"
#2190000
b1 '
1"
#2200000
0"
#2210000
b10 '
1"
#2220000
0"
#2230000
b11 '
1"
#2240000
0"
#2250000
b100 '
1"
#2260000
0"
#2270000
b101 '
1"
#2280000
0"
#2290000
b110 '
1"
